README.rst
setup.py
passage/__init__.py
passage/activations.py
passage/costs.py
passage/inits.py
passage/iterators.py
passage/layers.py
passage/models.py
passage/preprocessing.py
passage/theano_utils.py
passage/updates.py
passage/utils.py
passage.egg-info/PKG-INFO
passage.egg-info/SOURCES.txt
passage.egg-info/dependency_links.txt
passage.egg-info/requires.txt
passage.egg-info/top_level.txt