Metadata-Version: 1.0
Name: passage
Version: 0.2.4
Summary: 
Home-page: https://github.com/IndicoDataSolutions/Passage
Author: Alec Radford, Madison May
Author-email: 
License: MIT License (See LICENSE)
Platform: UNKNOWN
